rag_lib/.gitkeep
rag_lib/__init__.py
rag_lib/answer_generation/__init__.py
rag_lib/answer_generation/answer_generation.py
rag_lib/chunker/__init__.py
rag_lib/chunker/chunker.py
rag_lib/clearer/__init__.py
rag_lib/clearer/clearer.py
rag_lib/config.py
rag_lib/converter/__init__.py
rag_lib/converter/converter.py
rag_lib/deprecated_rag_api.py
rag_lib/deprecated_rag_lib.py
rag_lib/embedding/__init__.py
rag_lib/embedding/embedding_model.py
rag_lib/indexer/__init__.py
rag_lib/indexer/indexer.py
rag_lib/llm/__init__.py
rag_lib/llm/llm.py
rag_lib/pipeline/__init__.py
rag_lib/pipeline/RAGDataPipeline.py
rag_lib/pipeline/RAGPipeline.py
rag_lib/prompt/__init__.py
rag_lib/prompt/prompt_augmentation.py
rag_lib/retriever/__init__.py
rag_lib/retriever/retriever.py
rag_lib-0.1.0.dist-info/METADATA
rag_lib-0.1.0.dist-info/WHEEL
rag_lib-0.1.0.dist-info/RECORD
